{
  "current": {
    "sections": {
      "header": {
        "type": "header",
        "settings": {
        }
      },
      "banner": {
        "type": "banner",
        "settings": {
          "image": "shopify:\/\/shop_images\/illustration-30.png",
          "title": "My Bannere Section default Heading text",
          "description": "My Banner section default Paragraph",
          "cta_left": "Get Started",
          "cta_right": "1 St page",
          "button_link": "shopify:\/\/pages\/1st-page"
        }
      },
      "footer": {
        "type": "footer",
        "settings": {
        }
      },
      "16295780636f7a706b": {
        "type": "banner",
        "settings": {
          "title": "My Bannere Section default Heading text",
          "description": "My Banner section default Paragraph",
          "cta_left": "Get Started",
          "cta_right": "Play Video",
          "button_link": ""
        }
      }
    },
    "content_for_index": [
      "16295780636f7a706b"
    ]
  }
}
